[{
    "project": "Ember", 
    "location": "Bankstown",
    "budget": "80,000",
    "manager": "Rebecca Graham",
    "status": "Incomplete",
    "urgency": "High"
}, {
    "project": "Sunset", 
    "location": "Northern Beaches",
    "budget": "100,000",
    "manager": "Bruce Edgecombe",
    "status": "Incomplete",
    "urgency": "High"
}, {
    "project": "Nightwish", 
    "location": "Katoomba",
    "budget": "65,000",
    "manager": "Jane O'Neill",
    "status": "Complete",
    "urgency": "Low"
}, {
    "project": "Longhorne", 
    "location": "Bondi",
    "budget": "60,000",
    "manager": "Kaylee Edwards",
    "status": "Incomplete",
    "urgency": "Medium"
},  {
    "project": "Cascade", 
    "location": "Milson's Point",
    "budget": "70,000",
    "manager": "Richard Pine",
    "status": "Incomplete",
    "urgency": "Low"
}, {
    "project": "Whistler", 
    "location": "Dean Park",
    "budget": "30,000",
    "manager": "Samantha Carter",
    "status": "Complete",
    "urgency": "Low"
}, {
    "project": "Zoomer", 
    "location": "Dulwich",
    "budget": "60,000",
    "manager": "Martin Smith",
    "status": "Incomplete",
    "urgency": "Low"
}, {
    "project": "Next", 
    "location": "Earlwood",
    "budget": "90,000",
    "manager": "Jennifer Brown",
    "status": "Incomplete",
    "urgency": "High"
}, {
    "project": "Charlie", 
    "location": "Heathcote",
    "budget": "120,000",
    "manager": "David Miller",
    "status": "Incomplete",
    "urgency": "High"
}, {
    "project": "Razor", 
    "location": "Ingleburn",
    "budget": "110,000",
    "manager": "Taylor Millington",
    "status": "Incomplete",
    "urgency": "High"
}, {
    "project": "Jaguar", 
    "location": "Lakemba",
    "budget": "70,000",
    "manager": "Jake White",
    "status": "Complete",
    "urgency": "Low"
}, {
    "project": "Vista", 
    "location": "Macquarie Fields",
    "budget": "120,000",
    "manager": "Clark Kent",
    "status": "Incomplete",
    "urgency": "Medium"
}, {
    "project": "Experience", 
    "location": "Dee Why",
    "budget": "10,000",
    "manager": "Fraiser Crane",
    "status": "Incomplete",
    "urgency": "Low"
}, {
    "project": "Impact", 
    "location": "Maroota",
    "budget": "50,000",
    "manager": "Yasmin Young",
    "status": "Incomplete",
    "urgency": "Medium"
}, {
    "project": "Apollo", 
    "location": "Silverwater",
    "budget": "20,000",
    "manager": "Scott Parsons",
    "status": "Incomplete",
    "urgency": "Medium"
}, {
    "project": "Cyclone", 
    "location": "Picnic Point",
    "budget": "80,000",
    "manager": "Jeff Greene",
    "status": "Complete",
    "urgency": "High"
}, {
    "project": "Cairo", 
    "location": "Dee Why",
    "budget": "90,000",
    "manager": "Shane Hall",
    "status": "Incomplete",
    "urgency": "Low"
}]